setup.py
ansible_subprocess/__init__.py
ansible_subprocess/main.py
ansible_subprocess.egg-info/PKG-INFO
ansible_subprocess.egg-info/SOURCES.txt
ansible_subprocess.egg-info/dependency_links.txt
ansible_subprocess.egg-info/top_level.txt