Metadata-Version: 1.1
Name: ansible-subprocess
Version: 0.2.0
Summary: Using Ansible from python subprocess.
Home-page: https://github.com/uehara1414/ansible-subprocess
Author: uehara1414
Author-email: UNKNOWN
License: MIT License
Keywords: python Ansible subprocess
Platform: UNKNOWN
Classifier: Programming Language :: Python
Classifier: Programming Language :: Python :: 3
